source_quickbooks/__init__.py
source_quickbooks/manifest.yaml
source_quickbooks/run.py
source_quickbooks/source.py
airbyte_source_quickbooks-4.0.4.dist-info/METADATA
airbyte_source_quickbooks-4.0.4.dist-info/WHEEL
airbyte_source_quickbooks-4.0.4.dist-info/entry_points.txt
airbyte_source_quickbooks-4.0.4.dist-info/RECORD
