Metadata-Version: 2.3
Name: airbyte-source-quickbooks
Version: 4.0.4
Summary: Source implementation for quickbooks.
License: MIT
Author: Airbyte
Author-email: contact@airbyte.io
Requires-Python: >=3.10,<3.12
Classifier: License :: OSI Approved :: MIT License
Classifier: Programming Language :: Python :: 3
Classifier: Programming Language :: Python :: 3.10
Classifier: Programming Language :: Python :: 3.11
Requires-Dist: airbyte-cdk (>=4,<5)
Requires-Dist: urllib3 (==1.26.18)
Requires-Dist: vcrpy (==4.1.1)
Project-URL: Documentation, https://docs.airbyte.com/integrations/sources/quickbooks
Project-URL: Homepage, https://airbyte.com
Project-URL: Repository, https://github.com/airbytehq/airbyte
